ai_subtitle-0.1.4.dist-info/licenses/LICENSE
ai_subtitle_assistant/__init__.py
ai_subtitle_assistant/__main__.py
ai_subtitle_assistant/config.py
ai_subtitle_assistant/i18n.py
ai_subtitle_assistant/commands/__init__.py
ai_subtitle_assistant/commands/config_cmd.py
ai_subtitle_assistant/commands/transcribe_cmd.py
ai_subtitle_assistant/commands/translate_cmd.py
ai_subtitle_assistant/core/__init__.py
ai_subtitle_assistant/core/srt_utils.py
ai_subtitle_assistant/core/transcription.py
ai_subtitle_assistant/core/translation.py
ai_subtitle_assistant/core/video_utils.py
ai_subtitle-0.1.4.dist-info/METADATA
ai_subtitle-0.1.4.dist-info/WHEEL
ai_subtitle-0.1.4.dist-info/entry_points.txt
ai_subtitle-0.1.4.dist-info/top_level.txt
ai_subtitle-0.1.4.dist-info/RECORD
