Metadata-Version: 2.4
Name: ai-subtitle
Version: 0.1.4
Summary: A set of UNIX-style tools for generating and translating subtitles using AI.
Home-page: https://github.com/shdancer/ai-subtitle
Author: Lumos
Author-email: lumos@lumos.fit
Classifier: Programming Language :: Python :: 3
Classifier: License :: OSI Approved :: MIT License
Classifier: Operating System :: OS Independent
Requires-Python: >=3.7
License-File: LICENSE
Requires-Dist: openai
Requires-Dist: openai-whisper
Requires-Dist: ffmpeg-python
Requires-Dist: srt
Requires-Dist: platformdirs
Requires-Dist: colorama
Requires-Dist: polib
Requires-Dist: tqdm
Dynamic: author
Dynamic: author-email
Dynamic: classifier
Dynamic: description
Dynamic: description-content-type
Dynamic: home-page
Dynamic: license-file
Dynamic: requires-dist
Dynamic: requires-python
Dynamic: summary
